[
  {
    "종목명": "파마리서치",
    "고가등락률": 11,
    "고가발생시간": "10:50",
    "크기": 250,
    "섹터": "섹터",
    "색상": "#ffffff",
    "메모": "",
    "시장": "KOSPI",
    "xRatio": 49.33333333333333,
    "yRatio": 30.357142857142858
  },
  {
    "종목명": "파마리서치",
    "고가등락률": 14.7,
    "고가발생시간": "13:30",
    "크기": 100,
    "섹터": "",
    "색상": "#000000",
    "메모": "",
    "시장": "KOSPI",
    "xRatio": 59.2,
    "yRatio": 58.92857142857143
  },
  {
    "종목명": "싸이닉솔루션",
    "고가등락률": 6.3,
    "고가발생시간": "09:20",
    "크기": 150,
    "섹터": "신규주",
    "색상": "#caff63",
    "메모": "",
    "시장": "KOSPI",
    "xRatio": 36.8,
    "yRatio": 14.285714285714285
  },
  {
    "종목명": "싸이닉솔루션",
    "고가등락률": 11.2,
    "고가발생시간": "10:00",
    "크기": 150,
    "섹터": "신규주",
    "색상": "#caff63",
    "메모": "",
    "시장": "KOSPI",
    "xRatio": 49.86666666666666,
    "yRatio": 21.428571428571427
  },
  {
    "종목명": "싸이닉솔루션",
    "고가등락률": 16.5,
    "고가발생시간": "10:30",
    "크기": 150,
    "섹터": "신규주",
    "색상": "#caff63",
    "메모": "",
    "시장": "KOSPI",
    "xRatio": 64,
    "yRatio": 26.785714285714285
  },
  {
    "종목명": "싸이닉솔루션",
    "고가등락률": 23.5,
    "고가발생시간": "11:40",
    "크기": 100,
    "섹터": "신규주",
    "색상": "#caff63",
    "메모": "",
    "시장": "KOSPI",
    "xRatio": 82.66666666666666,
    "yRatio": 39.285714285714285
  },
  {
    "종목명": "싸이닉솔루션",
    "고가등락률": 23,
    "고가발생시간": "12:40",
    "크기": 50,
    "섹터": "신규주",
    "색상": "#caff63",
    "메모": "",
    "시장": "KOSPI",
    "xRatio": 81.33333333333334,
    "yRatio": 50
  },
  {
    "종목명": "싸이닉솔루션",
    "고가등락률": 28,
    "고가발생시간": "14:00",
    "크기": 150,
    "섹터": "신규주",
    "색상": "#caff63",
    "메모": "",
    "시장": "KOSPI",
    "xRatio": 94.66666666666667,
    "yRatio": 64.28571428571428
  },
  {
    "종목명": "알테오젠",
    "고가등락률": 0,
    "고가발생시간": "09:00",
    "크기": 100,
    "섹터": "바이오",
    "색상": "#28daff",
    "메모": "",
    "시장": "KOSPI",
    "xRatio": 20,
    "yRatio": 10.714285714285714
  },
  {
    "종목명": "알테오젠",
    "고가등락률": 1,
    "고가발생시간": "12:50",
    "크기": 100,
    "섹터": "바이오",
    "색상": "#28daff",
    "메모": "",
    "시장": "KOSPI",
    "xRatio": 22.666666666666668,
    "yRatio": 51.785714285714285
  },
  {
    "종목명": "알테오젠",
    "고가등락률": 1,
    "고가발생시간": "14:30",
    "크기": 50,
    "섹터": "바이오",
    "색상": "#28daff",
    "메모": "",
    "시장": "KOSPI",
    "xRatio": 22.666666666666668,
    "yRatio": 69.64285714285714
  },
  {
    "종목명": "뉴엔AI",
    "고가등락률": 7.8,
    "고가발생시간": "09:20",
    "크기": 100,
    "섹터": "신규주",
    "색상": "#caff63",
    "메모": "",
    "시장": "KOSPI",
    "xRatio": 40.8,
    "yRatio": 14.285714285714285
  },
  {
    "종목명": "뉴엔AI",
    "고가등락률": 17.1,
    "고가발생시간": "14:40",
    "크기": 200,
    "섹터": "신규주",
    "색상": "#caff63",
    "메모": "",
    "시장": "KOSPI",
    "xRatio": 65.60000000000001,
    "yRatio": 71.42857142857143
  },
  {
    "종목명": "쿠콘",
    "고가등락률": 13,
    "고가발생시간": "08:20",
    "크기": 200,
    "섹터": "지역화폐",
    "색상": "#6b917a",
    "메모": "",
    "시장": "KOSDAQ",
    "xRatio": 54.66666666666667,
    "yRatio": 3.571428571428571
  },
  {
    "종목명": "쿠콘",
    "고가등락률": 15,
    "고가발생시간": "09:00",
    "크기": 200,
    "섹터": "지역화폐",
    "색상": "#6b917a",
    "메모": "",
    "시장": "KOSDAQ",
    "xRatio": 60,
    "yRatio": 10.714285714285714
  },
  {
    "종목명": "다날",
    "고가등락률": -3.7,
    "고가발생시간": "10:00",
    "크기": 50,
    "섹터": "스테이블 코인",
    "색상": "#d9b359",
    "메모": "",
    "시장": "KOSDAQ",
    "xRatio": 17.533333333333335,
    "yRatio": 21.428571428571427
  },
  {
    "종목명": "미트박스",
    "고가등락률": 27.73,
    "고가발생시간": "12:30",
    "크기": 100,
    "섹터": "음식료",
    "색상": "#ffd220",
    "메모": "",
    "시장": "KOSDAQ",
    "xRatio": 93.94666666666667,
    "yRatio": 48.214285714285715
  },
  {
    "종목명": "미트박스",
    "고가등락률": 19,
    "고가발생시간": "11:40",
    "크기": 50,
    "섹터": "음식료",
    "색상": "#ffd220",
    "메모": "",
    "시장": "KOSDAQ",
    "xRatio": 70.66666666666666,
    "yRatio": 39.285714285714285
  },
  {
    "종목명": "미트박스",
    "고가등락률": 7.2,
    "고가발생시간": "09:00",
    "크기": 50,
    "섹터": "음식료",
    "색상": "#ffd220",
    "메모": "",
    "시장": "KOSDAQ",
    "xRatio": 39.2,
    "yRatio": 10.714285714285714
  },
  {
    "종목명": "실리콘투",
    "고가등락률": 5,
    "고가발생시간": "09:10",
    "크기": 100,
    "섹터": "화장품",
    "색상": "#ff8092",
    "메모": "",
    "시장": "KOSDAQ",
    "xRatio": 33.33333333333333,
    "yRatio": 12.5
  },
  {
    "종목명": "삼륭물산",
    "고가등락률": 28.51,
    "고가발생시간": "14:50",
    "크기": 50,
    "섹터": "탈플라스틱",
    "색상": "#39e75e",
    "메모": "",
    "시장": "KOSDAQ",
    "xRatio": 96.02666666666667,
    "yRatio": 73.21428571428571
  },
  {
    "종목명": "삼륭물산",
    "고가등락률": 23,
    "고가발생시간": "10:40",
    "크기": 50,
    "섹터": "탈플라스틱",
    "색상": "#39e75e",
    "메모": "",
    "시장": "KOSDAQ",
    "xRatio": 81.33333333333334,
    "yRatio": 28.57142857142857
  },
  {
    "종목명": "현대ADM",
    "고가등락률": 28,
    "고가발생시간": "09:00",
    "크기": 50,
    "섹터": "바이오",
    "색상": "#28daff",
    "메모": "",
    "시장": "KOSDAQ",
    "xRatio": 94.66666666666667,
    "yRatio": 10.714285714285714
  },
  {
    "종목명": "NHN KCP",
    "고가등락률": 8.3,
    "고가발생시간": "08:40",
    "크기": 50,
    "섹터": "스테이블 코인",
    "색상": "#d9b359",
    "메모": "",
    "시장": "KOSDAQ",
    "xRatio": 42.13333333333333,
    "yRatio": 7.142857142857142
  },
  {
    "종목명": "에이비엘바이오",
    "고가등락률": 5.02,
    "고가발생시간": "09:00",
    "크기": 50,
    "섹터": "바이오",
    "색상": "#28daff",
    "메모": "",
    "시장": "KOSDAQ",
    "xRatio": 33.38666666666666,
    "yRatio": 10.714285714285714
  },
  {
    "종목명": "로보티즈",
    "고가등락률": 5.3,
    "고가발생시간": "08:40",
    "크기": 50,
    "섹터": "로봇",
    "색상": "#818fc9",
    "메모": "",
    "시장": "KOSPI",
    "xRatio": 34.13333333333333,
    "yRatio": 7.142857142857142
  },
  {
    "종목명": "이브이첨단소재",
    "고가등락률": 15,
    "고가발생시간": "09:40",
    "크기": 50,
    "섹터": "2차전지",
    "색상": "#71e046",
    "메모": "",
    "시장": "KOSPI",
    "xRatio": 60,
    "yRatio": 17.857142857142858
  },
  {
    "종목명": "에코프로비엠",
    "고가등락률": 2.4,
    "고가발생시간": "09:00",
    "크기": 50,
    "섹터": "2차전지",
    "색상": "#71e046",
    "메모": "",
    "시장": "KOSPI",
    "xRatio": 26.4,
    "yRatio": 10.714285714285714
  },
  {
    "종목명": "디어유",
    "고가등락률": 9.3,
    "고가발생시간": "10:20",
    "크기": 50,
    "섹터": "엔터",
    "색상": "#3dff8b",
    "메모": "",
    "시장": "KOSPI",
    "xRatio": 44.8,
    "yRatio": 25
  },
  {
    "종목명": "상지건설",
    "고가등락률": 13.7,
    "고가발생시간": "10:50",
    "크기": 50,
    "섹터": "이재명",
    "색상": "#0D33B3",
    "메모": "",
    "시장": "KOSDAQ",
    "xRatio": 56.53333333333333,
    "yRatio": 30.357142857142858
  },
  {
    "종목명": "솔트룩스",
    "고가등락률": 10.07,
    "고가발생시간": "09:40",
    "크기": 100,
    "섹터": "AI",
    "색상": "#85b3d0",
    "메모": "",
    "시장": "KOSDAQ",
    "xRatio": 46.85333333333333,
    "yRatio": 17.857142857142858
  },
  {
    "종목명": "로킷헬스케어",
    "고가등락률": 3.8,
    "고가발생시간": "11:50",
    "크기": 50,
    "섹터": "의료AI",
    "색상": "#88accc",
    "메모": "",
    "시장": "KOSDAQ",
    "xRatio": 30.133333333333333,
    "yRatio": 41.07142857142858
  },
  {
    "종목명": "에코플라스틱",
    "고가등락률": 5.11,
    "고가발생시간": "10:40",
    "크기": 50,
    "섹터": "탈플라스틱",
    "색상": "#39e75e",
    "메모": "",
    "시장": "KOSDAQ",
    "xRatio": 33.626666666666665,
    "yRatio": 28.57142857142857
  },
  {
    "종목명": "현대바이오",
    "고가등락률": 7.8,
    "고가발생시간": "09:00",
    "크기": 50,
    "섹터": "바이오",
    "색상": "#28daff",
    "메모": "",
    "시장": "KOSDAQ",
    "xRatio": 40.8,
    "yRatio": 10.714285714285714
  },
  {
    "종목명": "파세코",
    "고가등락률": 3.1,
    "고가발생시간": "14:40",
    "크기": 50,
    "섹터": "폭염",
    "색상": "#EE0000",
    "메모": "",
    "시장": "KOSDAQ",
    "xRatio": 28.266666666666666,
    "yRatio": 71.42857142857143
  },
  {
    "종목명": "갤럭시아머니트리",
    "고가등락률": 6.3,
    "고가발생시간": "08:00",
    "크기": 100,
    "섹터": "스테이블 코인",
    "색상": "#d9b359",
    "메모": "",
    "시장": "KOSDAQ",
    "xRatio": 36.8,
    "yRatio": 0
  },
  {
    "종목명": "미투온",
    "고가등락률": 7.6,
    "고가발생시간": "09:00",
    "크기": 50,
    "섹터": "스테이블 코인",
    "색상": "#d9b359",
    "메모": "",
    "시장": "KOSDAQ",
    "xRatio": 40.266666666666666,
    "yRatio": 10.714285714285714
  },
  {
    "종목명": "오가노이드사이언스",
    "고가등락률": 6.2,
    "고가발생시간": "08:20",
    "크기": 50,
    "섹터": "바이오",
    "색상": "#28daff",
    "메모": "",
    "시장": "KOSDAQ",
    "xRatio": 36.53333333333333,
    "yRatio": 3.571428571428571
  },
  {
    "종목명": "한일사료",
    "고가등락률": 9,
    "고가발생시간": "12:40",
    "크기": 50,
    "섹터": "음식료",
    "색상": "#ffd220",
    "메모": "",
    "시장": "KOSDAQ",
    "xRatio": 44,
    "yRatio": 50
  },
  {
    "종목명": "비큐AI",
    "고가등락률": 12.04,
    "고가발생시간": "10:20",
    "크기": 50,
    "섹터": "AI",
    "색상": "#85b3d0",
    "메모": "",
    "시장": "KOSDAQ",
    "xRatio": 52.10666666666667,
    "yRatio": 25
  },
  {
    "종목명": "스튜디오미르",
    "고가등락률": 5.7,
    "고가발생시간": "09:40",
    "크기": 50,
    "섹터": "엔터",
    "색상": "#3dff8b",
    "메모": "",
    "시장": "KOSDAQ",
    "xRatio": 35.2,
    "yRatio": 17.857142857142858
  },
  {
    "종목명": "더즌",
    "고가등락률": 5.7,
    "고가발생시간": "09:30",
    "크기": 50,
    "섹터": "스테이블 코인",
    "색상": "#d9b359",
    "메모": "",
    "시장": "KOSDAQ",
    "xRatio": 35.2,
    "yRatio": 16.07142857142857
  },
  {
    "종목명": "더즌",
    "고가등락률": 6.7,
    "고가발생시간": "10:30",
    "크기": 50,
    "섹터": "스테이블 코인",
    "색상": "#d9b359",
    "메모": "",
    "시장": "KOSDAQ",
    "xRatio": 37.86666666666667,
    "yRatio": 26.785714285714285
  },
  {
    "종목명": "칩스앤미디어",
    "고가등락률": 2,
    "고가발생시간": "09:40",
    "크기": 50,
    "섹터": "반도체",
    "색상": "#ff9435",
    "메모": "",
    "시장": "KOSDAQ",
    "xRatio": 25.333333333333332,
    "yRatio": 17.857142857142858
  },
  {
    "종목명": "강원에너지",
    "고가등락률": 11,
    "고가발생시간": "09:20",
    "크기": 100,
    "섹터": "2차전지",
    "색상": "#71e046",
    "메모": "",
    "시장": "KOSDAQ",
    "xRatio": 49.33333333333333,
    "yRatio": 14.285714285714285
  },
  {
    "종목명": "옴니시스템",
    "고가등락률": 9,
    "고가발생시간": "14:40",
    "크기": 50,
    "섹터": "섹터",
    "색상": "#ffffff",
    "메모": "",
    "시장": "KOSPI",
    "xRatio": 44,
    "yRatio": 71.42857142857143
  }
]